Metadata-Version: 1.2
Name: hexdir
Version: 0.0.1a1
Summary: Create multi-level directory structures for hex filename repositories
Home-page: https://gitlab.com/nolash/hexdir
Author: Louis Holbrook
Author-email: dev@holbrook.no
License: GPL3
Keywords: filesystem,hex,directory
Platform: UNKNOWN
Classifier: Programming Language :: Python :: 3
Classifier: Operating System :: OS Independent
Classifier: Development Status :: 3 - Alpha
Classifier: Topic :: Software Development :: Libraries
Classifier: Environment :: Console
Classifier: Intended Audience :: Developers
Classifier: License :: OSI Approved :: GNU General Public License v3 or later (GPLv3+)
Classifier: Topic :: Internet
Requires-Python: >=3.6
